varman/__init__.py
varman-0.1.4.dist-info/LICENSE
varman-0.1.4.dist-info/METADATA
varman-0.1.4.dist-info/WHEEL
varman-0.1.4.dist-info/top_level.txt
varman-0.1.4.dist-info/RECORD
