Metadata-Version: 2.1
Name: varman
Version: 0.1.4
Summary: A dict like variable manager, listen for variable changes.
Home-page: https://github.com/zlolss/VarMan.py.git
Author: zloss
Author-email: zlols@foxmail.com
Classifier: Programming Language :: Python :: 3 :: Only
Classifier: License :: OSI Approved :: MIT License
Requires-Python: >=3.6
License-File: LICENSE
